hashbang/__init__.py
hashbang/_utils.py
hashbang/completion.py
hashbang/hashbang.py
hashbang-0.1.14.dist-info/LICENSE
hashbang-0.1.14.dist-info/METADATA
hashbang-0.1.14.dist-info/WHEEL
hashbang-0.1.14.dist-info/top_level.txt
hashbang-0.1.14.dist-info/RECORD
