Metadata-Version: 2.1
Name: hashbang
Version: 0.1.14
Summary: Turn Python functions into command line interfaces
Home-page: https://github.com/mauricelam/hashbang
Author: Maurice Lam
Author-email: mauriceprograms@gmail.com
License: UNKNOWN
Platform: UNKNOWN
Classifier: Programming Language :: Python :: 3
Classifier: Programming Language :: Python :: 3 :: Only
Classifier: License :: OSI Approved :: Apache Software License
Classifier: Operating System :: OS Independent
Classifier: Topic :: System :: Shells
Requires-Python: ~=3.4
Provides-Extra: completion
Requires-Dist: argcomplete ; extra == 'completion'
